upf_to_json/__init__.py
upf_to_json/upf1_to_json.py
upf_to_json/upf2_to_json.py
upf_to_json/upf_to_json.py
upf_to_json-1.0.0.dist-info/licenses/LICENSE
upf_to_json-1.0.0.dist-info/METADATA
upf_to_json-1.0.0.dist-info/WHEEL
upf_to_json-1.0.0.dist-info/entry_points.txt
upf_to_json-1.0.0.dist-info/top_level.txt
upf_to_json-1.0.0.dist-info/RECORD
