Metadata-Version: 2.4
Name: upf_to_json
Version: 1.0.0
Summary: upf to json converter
Author-email: Simon Pintarelli <simon.pintarelli@cscs.ch>
License: Copyright (c) 2013-2015 Anton Kozhevnikov, Thomas Schulthess
Project-URL: Homepage, https://github.com/simonpintarelli/upf_to_json
Classifier: Programming Language :: Python :: 3
Classifier: License :: OSI Approved :: BSD License
Classifier: Operating System :: OS Independent
Classifier: Programming Language :: Python :: 3.6
Classifier: Programming Language :: Python :: 3.7
Classifier: Programming Language :: Python :: 3.8
Classifier: Programming Language :: Python :: 3.9
Classifier: Programming Language :: Python :: 3.10
Classifier: Programming Language :: Python :: 3.11
Classifier: Topic :: Scientific/Engineering
License-File: LICENSE
Requires-Dist: Click
Provides-Extra: test
Requires-Dist: deepdiff; extra == "test"
Requires-Dist: pytest; extra == "test"
Dynamic: license-file
